ghr.py
ghr-1.0.7.dist-info/METADATA
ghr-1.0.7.dist-info/WHEEL
ghr-1.0.7.dist-info/top_level.txt
ghr-1.0.7.dist-info/RECORD
