Metadata-Version: 2.2
Name: ghr
Version: 1.0.7
Summary: A small tool to run repositories straight from GitHub.
Author-email: PabloMyLove <pablomylove@proton.me>
License: MIT
Project-URL: Homepage, https://github.com/PabloMyDarling/GitHub-Runner
Project-URL: Issues, https://github.com/PabloMyDarling/GitHub-Runner/issues
Classifier: Programming Language :: Python :: 3
Classifier: Operating System :: OS Independent
Requires-Python: >=3.10
Requires-Dist: requests
Requires-Dist: colorama
Requires-Dist: toml
